mock_call_where/__init__.py
mock_call_where/override.py
mock_call_where/pytest_plugin.py
mock_call_where-1.0.2.dist-info/LICENSE.txt
mock_call_where-1.0.2.dist-info/METADATA
mock_call_where-1.0.2.dist-info/WHEEL
mock_call_where-1.0.2.dist-info/entry_points.txt
mock_call_where-1.0.2.dist-info/top_level.txt
mock_call_where-1.0.2.dist-info/RECORD
