Metadata-Version: 2.1
Name: mock-call-where
Version: 1.0.2
Summary: A short little plugin to find where a mock was called!
Home-page: https://github.com/MrCocoDev/mock-call-where
Author: MrCocoDev
Author-email: 3229549+MrCocoDev@users.noreply.github.com
License: MIT
Project-URL: Documentation, https://pyscaffold.org/
Platform: any
Classifier: Development Status :: 5 - Production/Stable
Classifier: Framework :: Pytest
Classifier: Intended Audience :: Developers
Classifier: Programming Language :: Python
License-File: LICENSE.txt
Requires-Dist: importlib-metadata ; python_version < "3.8"
Provides-Extra: testing
Requires-Dist: setuptools ; extra == 'testing'
Requires-Dist: pytest ; extra == 'testing'
Requires-Dist: pytest-cov ; extra == 'testing'
